simple_AWS/__init__.py
simple_AWS/aws_functions.py
simple_AWS/cloudfront_functions.py
simple_AWS/dynamodb_functions.py
simple_AWS/ec2_functions.py
simple_AWS/s3_functions.py
simple_AWS/sns_functions.py
simple_AWS/sqs_functions.py
simple_AWS-0.1.6.dist-info/LICENSE
simple_AWS-0.1.6.dist-info/METADATA
simple_AWS-0.1.6.dist-info/WHEEL
simple_AWS-0.1.6.dist-info/top_level.txt
simple_AWS-0.1.6.dist-info/RECORD
