Metadata-Version: 2.1
Name: simple-AWS
Version: 0.1.6
Summary: Simplified AWS Functions
Home-page: https://github.com/maxpearl/simpleAWS
Author: Max Pearl
Author-email: code@maxwellpearl.com
License: GPLv3
Platform: UNKNOWN
Classifier: Development Status :: 2 - Pre-Alpha
Classifier: Topic :: Utilities
Requires-Python: >=3.3
License-File: LICENSE
Requires-Dist: botocore
Requires-Dist: boto3
